peeky/__init__.py
peeky/__main__.py
peeky/main.py
peeky/cli/__init__.py
peeky/cli/commands.py
peeky/cli/peeky_cli.py
peeky/core/__init__.py
peeky/core/config.py
peeky/core/network.py
peeky/core/process.py
peeky/core/secure.py
peeky/core/whois.py
peeky/formatters/__init__.py
peeky/formatters/export.py
peeky/formatters/security.py
peeky/formatters/tables.py
peeky/formatters/ui.py
peeky/formatters/whois.py
peeky-0.1.2.dist-info/licenses/LICENSE
peeky-0.1.2.dist-info/METADATA
peeky-0.1.2.dist-info/WHEEL
peeky-0.1.2.dist-info/entry_points.txt
peeky-0.1.2.dist-info/top_level.txt
peeky-0.1.2.dist-info/RECORD
