Metadata-Version: 2.4
Name: peeky
Version: 0.1.2
Summary: A Minimal Port & Process Inspector
Author-email: Amogh Agrawal <amogh.ggn@gmail.com>
License: MIT
Project-URL: Homepage, https://github.com/amogh-agrawal/peeky
Project-URL: Bug Tracker, https://github.com/amogh-agrawal/peeky/issues
Project-URL: Documentation, https://github.com/amogh-agrawal/peeky#readme
Keywords: network,ports,process,monitoring,cli,system,utilities
Classifier: Development Status :: 4 - Beta
Classifier: Environment :: Console
Classifier: Intended Audience :: Developers
Classifier: Intended Audience :: System Administrators
Classifier: License :: OSI Approved :: MIT License
Classifier: Operating System :: OS Independent
Classifier: Programming Language :: Python :: 3
Classifier: Programming Language :: Python :: 3.7
Classifier: Programming Language :: Python :: 3.8
Classifier: Programming Language :: Python :: 3.9
Classifier: Programming Language :: Python :: 3.10
Classifier: Programming Language :: Python :: 3.11
Classifier: Topic :: System :: Networking
Classifier: Topic :: System :: Monitoring
Classifier: Topic :: Utilities
Requires-Python: >=3.7
License-File: LICENSE
Requires-Dist: rich>=14.0.0
Requires-Dist: typer>=0.16.0
Requires-Dist: psutil>=7.0.0
Requires-Dist: click>=8.2.1
Requires-Dist: requests>=2.25.0
Provides-Extra: dev
Requires-Dist: pytest>=7.0.0; extra == "dev"
Requires-Dist: black>=23.0.0; extra == "dev"
Requires-Dist: isort>=5.12.0; extra == "dev"
Requires-Dist: flake8>=6.0.0; extra == "dev"
Dynamic: license-file
